cli_translate/__init__.py
cli_translate/core.py
cli_translate-0.0.5.dist-info/LICENSE.txt
cli_translate-0.0.5.dist-info/METADATA
cli_translate-0.0.5.dist-info/WHEEL
cli_translate-0.0.5.dist-info/entry_points.txt
cli_translate-0.0.5.dist-info/top_level.txt
cli_translate-0.0.5.dist-info/RECORD
