Metadata-Version: 2.1
Name: cli-translate
Version: 0.0.5
Summary: Useful translation tool for console. With features: translate text from clipboard and store translation logs
Home-page: https://github.com/Insolita/cli_translate
Author: Insolita
Author-email: webmaster100500@ya.ru
License: MIT
Download-URL: https://github.com/Insolita/cli_translate/tarball/master
Keywords: translation,translate,yandex,google,google translate,clipboard,notify-send,console
Platform: UNKNOWN
Classifier: Programming Language :: Python :: 3
Classifier: License :: OSI Approved :: MIT License
Requires-Python: >=3.4
Requires-Dist: pyperclip (>=1.5.27)
Requires-Dist: requests (>=2.18)
Requires-Dist: pyquery (>=1.2.9)
